{
 "run_at": "2026-07-19T02:55:42+00:00",
 "param_version": "assessor-v2.1.1.4018144e78",
 "mode": "LIVE",
 "status": "UNVERIFIED_PENDING_BOARD_REVIEW",
 "board_gate": "REQUIRED before any finding teaches or is implemented: the advisory board independently critiques these findings, cross-checks them against freshly-obtained outside data (current trending items, market/crypto movers), and verifies or refutes each. The CHAIRMAN has final say before any implementation.",
 "accuracy_headline": {
  "note": "THE accuracy number is the held-out ledger, not this tool",
  "tracked_race_hit_rate_pct": 24.2,
  "tracked_race_sample": 33,
  "tracked_race_wilson95_pct": [
   12.8,
   41.0
  ],
  "blended_hit_rate_pct": 9.2,
  "false_positives": 0,
  "false_positives_note": "structurally 0 until the 365d patience window matures rows \u2014 not a quality signal yet",
  "epoch_boundary": "2026-06-15",
  "by_epoch": {
   "v1_engine": {
    "resolved": 67,
    "led": 7,
    "hit_rate_pct": 10.4,
    "tracked_race_hit_rate_pct": 35.0,
    "tracked_race_sample": 20,
    "late_redetection_excluded": 5
   },
   "v2_engine": {
    "resolved": 20,
    "led": 1,
    "hit_rate_pct": 5.0,
    "tracked_race_hit_rate_pct": 7.7,
    "tracked_race_sample": 13,
    "late_redetection_excluded": 1
   }
  }
 },
 "operational_check_pass_pct": 98.6,
 "worst_module_floor_pct": 94.4,
 "internal_only": "never publish these percentages externally (catch-all-% rule)",
 "modules": {
  "A_SOURCES": {
   "grade": "A",
   "passed": 17,
   "graded": 17,
   "insufficient": 0,
   "severity_weighted_score": 1.0
  },
  "B_MOVEMENT": {
   "grade": "A",
   "passed": 51,
   "graded": 52,
   "insufficient": 0,
   "severity_weighted_score": 0.944
  },
  "C_ACCURACY": {
   "grade": "N/A (n=2<5)",
   "passed": 2,
   "graded": 2,
   "insufficient": 1
  },
  "D_LIFECYCLE": {
   "grade": "N/A",
   "passed": 0,
   "graded": 0,
   "insufficient": 0
  },
  "E_OUTSIDE": {
   "grade": "N/A",
   "passed": 0,
   "graded": 0,
   "insufficient": 2
  }
 },
 "cohort_spec": "ledger-enrolled(\u2229top200)=9 + top-served fill; n=60",
 "findings": [
  {
   "check": "A.freshness",
   "status": "PASS",
   "subject": "github",
   "evidence": "6024 signals 10m ago",
   "gap": "",
   "solution": "",
   "severity": "low",
   "task_class": "OPERATIONAL",
   "held_out_derived": false,
   "shadow": false,
   "ruling_id": "",
   "cause": ""
  },
  {
   "check": "A.freshness",
   "status": "PASS",
   "subject": "hackernews",
   "evidence": "135 signals 10m ago",
   "gap": "",
   "solution": "",
   "severity": "low",
   "task_class": "OPERATIONAL",
   "held_out_derived": false,
   "shadow": false,
   "ruling_id": "",
   "cause": ""
  },
  {
   "check": "A.freshness",
   "status": "PASS",
   "subject": "blogs",
   "evidence": "1690 signals 2m ago",
   "gap": "",
   "solution": "",
   "severity": "low",
   "task_class": "OPERATIONAL",
   "held_out_derived": false,
   "shadow": false,
   "ruling_id": "",
   "cause": ""
  },
  {
   "check": "A.freshness",
   "status": "PASS",
   "subject": "newsapi_org",
   "evidence": "195 signals 10m ago",
   "gap": "",
   "solution": "",
   "severity": "low",
   "task_class": "OPERATIONAL",
   "held_out_derived": false,
   "shadow": false,
   "ruling_id": "",
   "cause": ""
  },
  {
   "check": "A.freshness",
   "status": "PASS",
   "subject": "newsapi_ai",
   "evidence": "568 signals 10m ago",
   "gap": "",
   "solution": "",
   "severity": "low",
   "task_class": "OPERATIONAL",
   "held_out_derived": false,
   "shadow": false,
   "ruling_id": "",
   "cause": ""
  },
  {
   "check": "A.freshness",
   "status": "PASS",
   "subject": "newsdata_io",
   "evidence": "52 signals 9m ago",
   "gap": "",
   "solution": "",
   "severity": "low",
   "task_class": "OPERATIONAL",
   "held_out_derived": false,
   "shadow": false,
   "ruling_id": "",
   "cause": ""
  },
  {
   "check": "A.freshness",
   "status": "PASS",
   "subject": "bluesky",
   "evidence": "471 signals 7m ago",
   "gap": "",
   "solution": "",
   "severity": "low",
   "task_class": "OPERATIONAL",
   "held_out_derived": false,
   "shadow": false,
   "ruling_id": "",
   "cause": ""
  },
  {
   "check": "A.freshness",
   "status": "PASS",
   "subject": "lemmy",
   "evidence": "324 signals 7m ago",
   "gap": "",
   "solution": "",
   "severity": "low",
   "task_class": "OPERATIONAL",
   "held_out_derived": false,
   "shadow": false,
   "ruling_id": "",
   "cause": ""
  },
  {
   "check": "A.freshness",
   "status": "PASS",
   "subject": "mastodon",
   "evidence": "139 signals 7m ago",
   "gap": "",
   "solution": "",
   "severity": "low",
   "task_class": "OPERATIONAL",
   "held_out_derived": false,
   "shadow": false,
   "ruling_id": "",
   "cause": ""
  },
  {
   "check": "A.freshness",
   "status": "PASS",
   "subject": "google_trends",
   "evidence": "949 signals 145m ago",
   "gap": "",
   "solution": "",
   "severity": "low",
   "task_class": "OPERATIONAL",
   "held_out_derived": false,
   "shadow": false,
   "ruling_id": "",
   "cause": ""
  },
  {
   "check": "A.freshness",
   "status": "PASS",
   "subject": "youtube",
   "evidence": "12 signals 3m ago",
   "gap": "",
   "solution": "",
   "severity": "low",
   "task_class": "OPERATIONAL",
   "held_out_derived": false,
   "shadow": false,
   "ruling_id": "",
   "cause": ""
  },
  {
   "check": "A.freshness",
   "status": "PASS",
   "subject": "gdelt",
   "evidence": "145 signals 4m ago",
   "gap": "",
   "solution": "",
   "severity": "low",
   "task_class": "OPERATIONAL",
   "held_out_derived": false,
   "shadow": false,
   "ruling_id": "",
   "cause": ""
  },
  {
   "check": "A.freshness",
   "status": "PASS",
   "subject": "creators",
   "evidence": "273 signals 3m ago",
   "gap": "",
   "solution": "",
   "severity": "low",
   "task_class": "OPERATIONAL",
   "held_out_derived": false,
   "shadow": false,
   "ruling_id": "",
   "cause": ""
  },
  {
   "check": "A.freshness",
   "status": "PASS",
   "subject": "broadcast",
   "evidence": "2714 signals 3m ago",
   "gap": "",
   "solution": "",
   "severity": "low",
   "task_class": "OPERATIONAL",
   "held_out_derived": false,
   "shadow": false,
   "ruling_id": "",
   "cause": ""
  },
  {
   "check": "A.freshness",
   "status": "PASS",
   "subject": "risk",
   "evidence": "1514 signals 32m ago",
   "gap": "",
   "solution": "",
   "severity": "low",
   "task_class": "OPERATIONAL",
   "held_out_derived": false,
   "shadow": false,
   "ruling_id": "",
   "cause": ""
  },
  {
   "check": "A.freshness",
   "status": "PASS",
   "subject": "alphavantage",
   "evidence": "16 signals 32m ago",
   "gap": "",
   "solution": "",
   "severity": "low",
   "task_class": "OPERATIONAL",
   "held_out_derived": false,
   "shadow": false,
   "ruling_id": "",
   "cause": ""
  },
  {
   "check": "A.freshness",
   "status": "DEFERRED",
   "subject": "reddit",
   "evidence": "DEGRADED \u2014 founder-deferred credentials (ran 12m ago but 0 signals)",
   "gap": "",
   "solution": "",
   "severity": "low",
   "task_class": "OPERATIONAL",
   "held_out_derived": false,
   "shadow": false,
   "ruling_id": "",
   "cause": ""
  },
  {
   "check": "A.silent_absence",
   "status": "PASS",
   "subject": "collector fleet",
   "evidence": "16 healthy / 1 degraded / 0 stale / 0 down (of 17; trust: All critical collectors healthy.)",
   "gap": "",
   "solution": "",
   "severity": "low",
   "task_class": "OPERATIONAL",
   "held_out_derived": false,
   "shadow": false,
   "ruling_id": "",
   "cause": ""
  },
  {
   "check": "B.volatility",
   "status": "PASS",
   "subject": "mamdani",
   "evidence": "burst dynamics (std 24.3, 0 flips, range 24.7\u201390; series: 24.7,89.9,89.95,89.9,90,90) \u2014 monotone step/cliff, expected for bursty attention",
   "gap": "",
   "solution": "",
   "severity": "low",
   "task_class": "OPERATIONAL",
   "held_out_derived": false,
   "shadow": false,
   "ruling_id": "",
   "cause": ""
  },
  {
   "check": "B.volatility",
   "status": "PASS",
   "subject": "trump",
   "evidence": "near-static (std 0.8, range 86.62\u201388.32) \u2014 see B.freeze null condition; NOT asserted as 'moving normally'",
   "gap": "",
   "solution": "",
   "severity": "low",
   "task_class": "OPERATIONAL",
   "held_out_derived": false,
   "shadow": false,
   "ruling_id": "",
   "cause": ""
  },
  {
   "check": "B.volatility",
   "status": "PASS",
   "subject": "mexico",
   "evidence": "within normal dispersion (std 9.7, range 60.6\u201381.3, 0 flips)",
   "gap": "",
   "solution": "",
   "severity": "low",
   "task_class": "OPERATIONAL",
   "held_out_derived": false,
   "shadow": false,
   "ruling_id": "",
   "cause": ""
  },
  {
   "check": "B.volatility",
   "status": "PASS",
   "subject": "socialists",
   "evidence": "burst dynamics (std 34.8, 0 flips, range 9\u201383.85; series: 9.4,9,9.5,12.6,83.85,83.85) \u2014 monotone step/cliff, expected for bursty attention",
   "gap": "",
   "solution": "",
   "severity": "low",
   "task_class": "OPERATIONAL",
   "held_out_derived": false,
   "shadow": false,
   "ruling_id": "",
   "cause": ""
  },
  {
   "check": "B.volatility",
   "status": "PASS",
   "subject": "andy_burnham",
   "evidence": "near-static (std 0.1, range 63.47\u201363.64) \u2014 see B.freeze null condition; NOT asserted as 'moving normally'",
   "gap": "",
   "solution": "",
   "severity": "low",
   "task_class": "OPERATIONAL",
   "held_out_derived": false,
   "shadow": false,
   "ruling_id": "",
   "cause": ""
  },
  {
   "check": "B.volatility",
   "status": "PASS",
   "subject": "us_and_iran",
   "evidence": "within normal dispersion (std 7.2, range 16.7\u201337.39, 0 flips)",
   "gap": "",
   "solution": "",
   "severity": "low",
   "task_class": "OPERATIONAL",
   "held_out_derived": false,
   "shadow": false,
   "ruling_id": "",
   "cause": ""
  },
  {
   "check": "B.volatility",
   "status": "PASS",
   "subject": "strait_of_hormuz",
   "evidence": "within normal dispersion (std 5.3, range 22.5\u201336.79, 0 flips)",
   "gap": "",
   "solution": "",
   "severity": "low",
   "task_class": "OPERATIONAL",
   "held_out_derived": false,
   "shadow": false,
   "ruling_id": "",
   "cause": ""
  },
  {
   "check": "B.volatility",
   "status": "PASS",
   "subject": "ai_agents",
   "evidence": "near-static (std 0.2, range 35.1\u201335.5) \u2014 see B.freeze null condition; NOT asserted as 'moving normally'",
   "gap": "",
   "solution": "",
   "severity": "low",
   "task_class": "OPERATIONAL",
   "held_out_derived": false,
   "shadow": false,
   "ruling_id": "",
   "cause": ""
  },
  {
   "check": "B.volatility",
   "status": "PASS",
   "subject": "fifa",
   "evidence": "burst dynamics (std 16.9, 2 flips, range 29.56\u201376.05; series: 74.6,74.6,72.96,54.92,76.05,29.56) \u2014 monotone step/cliff, expected for bursty attention",
   "gap": "",
   "solution": "",
   "severity": "low",
   "task_class": "OPERATIONAL",
   "held_out_derived": false,
   "shadow": false,
   "ruling_id": "",
   "cause": ""
  },
  {
   "check": "B.volatility",
   "status": "PASS",
   "subject": "rikers",
   "evidence": "near-static (std 1.0, range 94.2\u201396.64) \u2014 see B.freeze null condition; NOT asserted as 'moving normally'",
   "gap": "",
   "solution": "",
   "severity": "low",
   "task_class": "OPERATIONAL",
   "held_out_derived": false,
   "shadow": false,
   "ruling_id": "",
   "cause": ""
  },
  {
   "check": "B.volatility",
   "status": "PASS",
   "subject": "agi",
   "evidence": "near-static (std 0.0, range 92.23\u201392.28) \u2014 see B.freeze null condition; NOT asserted as 'moving normally'",
   "gap": "",
   "solution": "",
   "severity": "low",
   "task_class": "OPERATIONAL",
   "held_out_derived": false,
   "shadow": false,
   "ruling_id": "",
   "cause": ""
  },
  {
   "check": "B.volatility",
   "status": "PASS",
   "subject": "cyclospora",
   "evidence": "within normal dispersion (std 7.1, range 70.97\u201390.73, 0 flips)",
   "gap": "",
   "solution": "",
   "severity": "low",
   "task_class": "OPERATIONAL",
   "held_out_derived": false,
   "shadow": false,
   "ruling_id": "",
   "cause": ""
  },
  {
   "check": "B.volatility",
   "status": "PASS",
   "subject": "rag",
   "evidence": "burst dynamics (std 12.7, 1 flips, range 62.51\u201389.93; series: 89.93,89.93,62.51,62.51,89.09,89.09) \u2014 monotone step/cliff, expected for bursty attention",
   "gap": "",
   "solution": "",
   "severity": "low",
   "task_class": "OPERATIONAL",
   "held_out_derived": false,
   "shadow": false,
   "ruling_id": "",
   "cause": ""
  },
  {
   "check": "B.volatility",
   "status": "PASS",
   "subject": "taco_bell",
   "evidence": "burst dynamics (std 27.4, 0 flips, range 16.2\u201392.24; series: 16.2,80.99,89.33,90.69,91.75,92.24) \u2014 monotone step/cliff, expected for bursty attention",
   "gap": "",
   "solution": "",
   "severity": "low",
   "task_class": "OPERATIONAL",
   "held_out_derived": false,
   "shadow": false,
   "ruling_id": "",
   "cause": ""
  },
  {
   "check": "B.volatility",
   "status": "PASS",
   "subject": "canada",
   "evidence": "within normal dispersion (std 1.6, range 88.32\u201391.69, 0 flips)",
   "gap": "",
   "solution": "",
   "severity": "low",
   "task_class": "OPERATIONAL",
   "held_out_derived": false,
   "shadow": false,
   "ruling_id": "",
   "cause": ""
  },
  {
   "check": "B.volatility",
   "status": "PASS",
   "subject": "wildfires",
   "evidence": "near-static (std 0.0, range 87.66\u201387.68) \u2014 see B.freeze null condition; NOT asserted as 'moving normally'",
   "gap": "",
   "solution": "",
   "severity": "low",
   "task_class": "OPERATIONAL",
   "held_out_derived": false,
   "shadow": false,
   "ruling_id": "",
   "cause": ""
  },
  {
   "check": "B.volatility",
   "status": "PASS",
   "subject": "smoke_from_canada",
   "evidence": "burst dynamics (std 16.3, 0 flips, range 50.39\u201391.86; series: 50.39,63.88,89.61,90.05,90.88,91.86) \u2014 monotone step/cliff, expected for bursty attention",
   "gap": "",
   "solution": "",
   "severity": "low",
   "task_class": "OPERATIONAL",
   "held_out_derived": false,
   "shadow": false,
   "ruling_id": "",
   "cause": ""
  },
  {
   "check": "B.volatility",
   "status": "PASS",
   "subject": "fifa_world_cup",
   "evidence": "within normal dispersion (std 7.8, range 62.4\u201384.02, 1 flips)",
   "gap": "",
   "solution": "",
   "severity": "low",
   "task_class": "OPERATIONAL",
   "held_out_derived": false,
   "shadow": false,
   "ruling_id": "",
   "cause": ""
  },
  {
   "check": "B.volatility",
   "status": "PASS",
   "subject": "russia",
   "evidence": "within normal dispersion (std 7.9, range 70.86\u201388.36, 1 flips)",
   "gap": "",
   "solution": "",
   "severity": "low",
   "task_class": "OPERATIONAL",
   "held_out_derived": false,
   "shadow": false,
   "ruling_id": "",
   "cause": ""
  },
  {
   "check": "B.volatility",
   "status": "PASS",
   "subject": "new_mexico",
   "evidence": "burst dynamics (std 28.5, 0 flips, range 18.4\u201380.8; series: 18.4,22.4,80.8,80.8,80.8,80.8) \u2014 monotone step/cliff, expected for bursty attention",
   "gap": "",
   "solution": "",
   "severity": "low",
   "task_class": "OPERATIONAL",
   "held_out_derived": false,
   "shadow": false,
   "ruling_id": "",
   "cause": ""
  },
  {
   "check": "B.volatility",
   "status": "PASS",
   "subject": "cyclosporiasis_outbreak",
   "evidence": "within normal dispersion (std 10.8, range 54.17\u201383.76, 0 flips)",
   "gap": "",
   "solution": "",
   "severity": "low",
   "task_class": "OPERATIONAL",
   "held_out_derived": false,
   "shadow": false,
   "ruling_id": "",
   "cause": ""
  },
  {
   "check": "B.volatility",
   "status": "PASS",
   "subject": "pricey",
   "evidence": "within normal dispersion (std 7.5, range 64.3\u201380.57, 2 flips)",
   "gap": "",
   "solution": "",
   "severity": "low",
   "task_class": "OPERATIONAL",
   "held_out_derived": false,
   "shadow": false,
   "ruling_id": "",
   "cause": ""
  },
  {
   "check": "B.volatility",
   "status": "PASS",
   "subject": "britain",
   "evidence": "burst dynamics (std 19.2, 1 flips, range 24\u201375.6; series: 75.52,75.52,75.52,24,75.6,75.56) \u2014 monotone step/cliff, expected for bursty attention",
   "gap": "",
   "solution": "",
   "severity": "low",
   "task_class": "OPERATIONAL",
   "held_out_derived": false,
   "shadow": false,
   "ruling_id": "",
   "cause": ""
  },
  {
   "check": "B.volatility",
   "status": "PASS",
   "subject": "brenda_fricker",
   "evidence": "burst dynamics (std 31.0, 0 flips, range 13.8\u201386.78; series: 13.8,19.4,23.4,29.6,86.37,86.78) \u2014 monotone step/cliff, expected for bursty attention",
   "gap": "",
   "solution": "",
   "severity": "low",
   "task_class": "OPERATIONAL",
   "held_out_derived": false,
   "shadow": false,
   "ruling_id": "",
   "cause": ""
  },
  {
   "check": "B.volatility",
   "status": "PASS",
   "subject": "primetime_address",
   "evidence": "within normal dispersion (std 5.2, range 60.63\u201375.74, 0 flips)",
   "gap": "",
   "solution": "",
   "severity": "low",
   "task_class": "OPERATIONAL",
   "held_out_derived": false,
   "shadow": false,
   "ruling_id": "",
   "cause": ""
  },
  {
   "check": "B.volatility",
   "status": "PASS",
   "subject": "agent",
   "evidence": "within normal dispersion (std 9.0, range 70.94\u201389.95, 0 flips)",
   "gap": "",
   "solution": "",
   "severity": "low",
   "task_class": "OPERATIONAL",
   "held_out_derived": false,
   "shadow": false,
   "ruling_id": "",
   "cause": ""
  },
  {
   "check": "B.volatility",
   "status": "PASS",
   "subject": "starmer",
   "evidence": "burst dynamics (std 21.7, 0 flips, range 25.9\u201372.19; series: 26.3,25.9,26.4,25.9,72.19,72.06) \u2014 monotone step/cliff, expected for bursty attention",
   "gap": "",
   "solution": "",
   "severity": "low",
   "task_class": "OPERATIONAL",
   "held_out_derived": false,
   "shadow": false,
   "ruling_id": "",
   "cause": ""
  },
  {
   "check": "B.volatility",
   "status": "PASS",
   "subject": "suno",
   "evidence": "within normal dispersion (std 5.8, range 61.46\u201376.01, 0 flips)",
   "gap": "",
   "solution": "",
   "severity": "low",
   "task_class": "OPERATIONAL",
   "held_out_derived": false,
   "shadow": false,
   "ruling_id": "",
   "cause": ""
  },
  {
   "check": "B.volatility",
   "status": "PASS",
   "subject": "scrolling",
   "evidence": "burst dynamics (std 33.0, 0 flips, range 14.2\u201384.84; series: 14.7,14.2,15.6,15.1,84.84,84.84) \u2014 monotone step/cliff, expected for bursty attention",
   "gap": "",
   "solution": "",
   "severity": "low",
   "task_class": "OPERATIONAL",
   "held_out_derived": false,
   "shadow": false,
   "ruling_id": "",
   "cause": ""
  },
  {
   "check": "B.volatility",
   "status": "PASS",
   "subject": "haze",
   "evidence": "burst dynamics (std 14.0, 0 flips, range 39.35\u201375.93; series: 39.35,51.97,53.93,75.29,73.6,75.93) \u2014 monotone step/cliff, expected for bursty attention",
   "gap": "",
   "solution": "",
   "severity": "low",
   "task_class": "OPERATIONAL",
   "held_out_derived": false,
   "shadow": false,
   "ruling_id": "",
   "cause": ""
  },
  {
   "check": "B.volatility",
   "status": "PASS",
   "subject": "europe",
   "evidence": "within normal dispersion (std 1.1, range 66.43\u201368.72, 0 flips)",
   "gap": "",
   "solution": "",
   "severity": "low",
   "task_class": "OPERATIONAL",
   "held_out_derived": false,
   "shadow": false,
   "ruling_id": "",
   "cause": ""
  },
  {
   "check": "B.volatility",
   "status": "PASS",
   "subject": "the_us",
   "evidence": "burst dynamics (std 17.7, 0 flips, range 30.32\u201368.02; series: 30.67,30.32,68.02,68.02,68.02,68.02) \u2014 monotone step/cliff, expected for bursty attention",
   "gap": "",
   "solution": "",
   "severity": "low",
   "task_class": "OPERATIONAL",
   "held_out_derived": false,
   "shadow": false,
   "ruling_id": "",
   "cause": ""
  },
  {
   "check": "B.volatility",
   "status": "PASS",
   "subject": "wildfire_smoke",
   "evidence": "within normal dispersion (std 2.8, range 67.99\u201375.41, 0 flips)",
   "gap": "",
   "solution": "",
   "severity": "low",
   "task_class": "OPERATIONAL",
   "held_out_derived": false,
   "shadow": false,
   "ruling_id": "",
   "cause": ""
  },
  {
   "check": "B.volatility",
   "status": "PASS",
   "subject": "whistleblower",
   "evidence": "burst dynamics (std 22.7, 1 flips, range 25.7\u201375.63; series: 32.3,26.3,26.2,25.7,75.63,75.63) \u2014 monotone step/cliff, expected for bursty attention",
   "gap": "",
   "solution": "",
   "severity": "low",
   "task_class": "OPERATIONAL",
   "held_out_derived": false,
   "shadow": false,
   "ruling_id": "",
   "cause": ""
  },
  {
   "check": "B.volatility",
   "status": "PASS",
   "subject": "taco",
   "evidence": "burst dynamics (std 24.5, 0 flips, range 15.3\u201381.31; series: 15.3,80.88,81.08,81.08,81.22,81.31) \u2014 monotone step/cliff, expected for bursty attention",
   "gap": "",
   "solution": "",
   "severity": "low",
   "task_class": "OPERATIONAL",
   "held_out_derived": false,
   "shadow": false,
   "ruling_id": "",
   "cause": ""
  },
  {
   "check": "B.volatility",
   "status": "PASS",
   "subject": "garfield_sobers",
   "evidence": "burst dynamics (std 29.1, 0 flips, range 10.8\u201379.06; series: 10.8,13.9,19.4,27.9,78.49,79.06) \u2014 monotone step/cliff, expected for bursty attention",
   "gap": "",
   "solution": "",
   "severity": "low",
   "task_class": "OPERATIONAL",
   "held_out_derived": false,
   "shadow": false,
   "ruling_id": "",
   "cause": ""
  },
  {
   "check": "B.volatility",
   "status": "PASS",
   "subject": "primetime",
   "evidence": "within normal dispersion (std 3.1, range 66.79\u201374.58, 0 flips)",
   "gap": "",
   "solution": "",
   "severity": "low",
   "task_class": "OPERATIONAL",
   "held_out_derived": false,
   "shadow": false,
   "ruling_id": "",
   "cause": ""
  },
  {
   "check": "B.volatility",
   "status": "PASS",
   "subject": "trump_election",
   "evidence": "burst dynamics (std 18.5, 0 flips, range 18.7\u201371.03; series: 18.7,61.61,66.67,68.72,70.33,71.03) \u2014 monotone step/cliff, expected for bursty attention",
   "gap": "",
   "solution": "",
   "severity": "low",
   "task_class": "OPERATIONAL",
   "held_out_derived": false,
   "shadow": false,
   "ruling_id": "",
   "cause": ""
  },
  {
   "check": "B.volatility",
   "status": "PASS",
   "subject": "odyssey",
   "evidence": "within normal dispersion (std 3.3, range 66.26\u201377.43, 0 flips)",
   "gap": "",
   "solution": "",
   "severity": "low",
   "task_class": "OPERATIONAL",
   "held_out_derived": false,
   "shadow": false,
   "ruling_id": "",
   "cause": ""
  },
  {
   "check": "B.volatility",
   "status": "PASS",
   "subject": "testosterone",
   "evidence": "within normal dispersion (std 7.5, range 69.08\u201388.15, 1 flips)",
   "gap": "",
   "solution": "",
   "severity": "low",
   "task_class": "OPERATIONAL",
   "held_out_derived": false,
   "shadow": false,
   "ruling_id": "",
   "cause": ""
  },
  {
   "check": "B.volatility",
   "status": "PASS",
   "subject": "lettuce",
   "evidence": "within normal dispersion (std 4.8, range 54.19\u201365.33, 0 flips)",
   "gap": "",
   "solution": "",
   "severity": "low",
   "task_class": "OPERATIONAL",
   "held_out_derived": false,
   "shadow": false,
   "ruling_id": "",
   "cause": ""
  },
  {
   "check": "B.volatility",
   "status": "PASS",
   "subject": "las_vegas_airport",
   "evidence": "burst dynamics (std 18.3, 0 flips, range 24.06\u201367.76; series: 24.06,27.89,61.08,64.1,65.15,67.76) \u2014 monotone step/cliff, expected for bursty attention",
   "gap": "",
   "solution": "",
   "severity": "low",
   "task_class": "OPERATIONAL",
   "held_out_derived": false,
   "shadow": false,
   "ruling_id": "",
   "cause": ""
  },
  {
   "check": "B.volatility",
   "status": "PASS",
   "subject": "primetime_speech",
   "evidence": "within normal dispersion (std 8.9, range 60.63\u201387.69, 0 flips)",
   "gap": "",
   "solution": "",
   "severity": "low",
   "task_class": "OPERATIONAL",
   "held_out_derived": false,
   "shadow": false,
   "ruling_id": "",
   "cause": ""
  },
  {
   "check": "B.volatility",
   "status": "PASS",
   "subject": "microsoft",
   "evidence": "within normal dispersion (std 1.8, range 58.28\u201363.06, 0 flips)",
   "gap": "",
   "solution": "",
   "severity": "low",
   "task_class": "OPERATIONAL",
   "held_out_derived": false,
   "shadow": false,
   "ruling_id": "",
   "cause": ""
  },
  {
   "check": "B.freeze",
   "status": "FAIL",
   "subject": "final_del_mundial",
   "evidence": "Detection identical at 62.59 for 6 cycles while mentions varied 10\u201316",
   "gap": "score not responding to changing inputs (possible cached serve or saturated components)",
   "solution": "check INV-1 serve-stored rules + serve_payload freshness for this row; inspect component values in the detail; report findings to the founder before any scoring change",
   "severity": "high",
   "task_class": "SCORE_AFFECTING",
   "held_out_derived": false,
   "shadow": false,
   "ruling_id": "",
   "cause": ""
  },
  {
   "check": "B.volatility",
   "status": "PASS",
   "subject": "trump_speech",
   "evidence": "burst dynamics (std 18.8, 0 flips, range 20.4\u201363.64; series: 20.4,23.4,25.8,26,63.64,63.5) \u2014 monotone step/cliff, expected for bursty attention",
   "gap": "",
   "solution": "",
   "severity": "low",
   "task_class": "OPERATIONAL",
   "held_out_derived": false,
   "shadow": false,
   "ruling_id": "",
   "cause": ""
  },
  {
   "check": "B.volatility",
   "status": "PASS",
   "subject": "slavko_vin\u010di\u0107",
   "evidence": "burst dynamics (std 26.7, 0 flips, range 12\u201372.94; series: 12,13.4,15.5,15,68.01,72.94) \u2014 monotone step/cliff, expected for bursty attention",
   "gap": "",
   "solution": "",
   "severity": "low",
   "task_class": "OPERATIONAL",
   "held_out_derived": false,
   "shadow": false,
   "ruling_id": "",
   "cause": ""
  },
  {
   "check": "B.volatility",
   "status": "PASS",
   "subject": "vegas_airport",
   "evidence": "burst dynamics (std 16.0, 2 flips, range 21.93\u201364.76; series: 21.93,26.52,59.63,52.56,43.13,64.76) \u2014 monotone step/cliff, expected for bursty attention",
   "gap": "",
   "solution": "",
   "severity": "low",
   "task_class": "OPERATIONAL",
   "held_out_derived": false,
   "shadow": false,
   "ruling_id": "",
   "cause": ""
  },
  {
   "check": "B.volatility",
   "status": "PASS",
   "subject": "meta",
   "evidence": "within normal dispersion (std 9.3, range 55.37\u201377.49, 2 flips)",
   "gap": "",
   "solution": "",
   "severity": "low",
   "task_class": "OPERATIONAL",
   "held_out_derived": false,
   "shadow": false,
   "ruling_id": "",
   "cause": ""
  },
  {
   "check": "B.volatility",
   "status": "PASS",
   "subject": "robert_pattinson",
   "evidence": "burst dynamics (std 25.8, 0 flips, range 9.1\u201368.94; series: 9.5,9.1,13.8,13.4,62.71,68.94) \u2014 monotone step/cliff, expected for bursty attention",
   "gap": "",
   "solution": "",
   "severity": "low",
   "task_class": "OPERATIONAL",
   "held_out_derived": false,
   "shadow": false,
   "ruling_id": "",
   "cause": ""
  },
  {
   "check": "B.volatility",
   "status": "PASS",
   "subject": "yassine_bounou",
   "evidence": "burst dynamics (std 24.0, 0 flips, range 5.8\u201370.97; series: 5.8,49.29,70.97,70.97,70.97,70.97) \u2014 monotone step/cliff, expected for bursty attention",
   "gap": "",
   "solution": "",
   "severity": "low",
   "task_class": "OPERATIONAL",
   "held_out_derived": false,
   "shadow": false,
   "ruling_id": "",
   "cause": ""
  },
  {
   "check": "B.freeze",
   "status": "PASS",
   "subject": "cohort",
   "evidence": "51 topics had >= 6 cycles of history",
   "gap": "",
   "solution": "",
   "severity": "low",
   "task_class": "OPERATIONAL",
   "held_out_derived": false,
   "shadow": false,
   "ruling_id": "",
   "cause": ""
  },
  {
   "check": "B.asymmetry",
   "status": "WARN",
   "subject": "britain",
   "evidence": "instant transitions BOTH ways in one window (max up 51.6, max down -51.5 in single cycles) \u2014 artifact signature, not attention dynamics",
   "gap": "quantized bistability: the estimator, not the phenomenon, is moving",
   "solution": "hold for the cohort replay verification (board Q1/Q2 item 3); no estimator change without founder + backtest (item 6 HELD)",
   "severity": "low",
   "task_class": "OPERATIONAL",
   "held_out_derived": false,
   "shadow": true,
   "ruling_id": "",
   "cause": ""
  },
  {
   "check": "B.asymmetry",
   "status": "PASS",
   "subject": "cohort asymmetry profile",
   "evidence": "19 topics with instant up-steps, 2 with instant down-steps, 1 with BOTH in one window (n=51; step floor 30.0)",
   "gap": "",
   "solution": "",
   "severity": "low",
   "task_class": "OPERATIONAL",
   "held_out_derived": false,
   "shadow": true,
   "ruling_id": "",
   "cause": ""
  },
  {
   "check": "C.gap_arithmetic",
   "status": "PASS",
   "subject": "60 rows",
   "evidence": "served gap = |Detection-Confidence| within tolerance on every row",
   "gap": "",
   "solution": "",
   "severity": "low",
   "task_class": "OPERATIONAL",
   "held_out_derived": false,
   "shadow": false,
   "ruling_id": "",
   "cause": ""
  },
  {
   "check": "C.alias_families",
   "status": "PASS",
   "subject": "alias review queue",
   "evidence": "0 pending alias candidates awaiting HUMAN review",
   "gap": "",
   "solution": "",
   "severity": "low",
   "task_class": "OPERATIONAL",
   "held_out_derived": false,
   "shadow": false,
   "ruling_id": "",
   "cause": ""
  },
  {
   "check": "C.saturation_gauge",
   "status": "PASS",
   "subject": "top-decile cap pinning",
   "evidence": "0/6 top-decile topics pinned at caps",
   "gap": "",
   "solution": "",
   "severity": "low",
   "task_class": "OPERATIONAL",
   "held_out_derived": false,
   "shadow": true,
   "ruling_id": "",
   "cause": ""
  },
  {
   "check": "C.referee_surge",
   "status": "PASS",
   "subject": "mamdani",
   "evidence": "surge-agreement ok (referee ratio 0.6x, Detection 90.0)",
   "gap": "",
   "solution": "",
   "severity": "low",
   "task_class": "OPERATIONAL",
   "held_out_derived": true,
   "shadow": true,
   "ruling_id": "",
   "cause": ""
  },
  {
   "check": "C.referee_surge",
   "status": "PASS",
   "subject": "Donald Trump",
   "evidence": "surge-agreement ok (referee ratio 1.0x, Detection 88.3)",
   "gap": "",
   "solution": "",
   "severity": "low",
   "task_class": "OPERATIONAL",
   "held_out_derived": true,
   "shadow": true,
   "ruling_id": "",
   "cause": ""
  },
  {
   "check": "C.referee_surge",
   "status": "PASS",
   "subject": "mexico",
   "evidence": "surge-agreement ok (referee ratio 0.9x, Detection 81.3)",
   "gap": "",
   "solution": "",
   "severity": "low",
   "task_class": "OPERATIONAL",
   "held_out_derived": true,
   "shadow": true,
   "ruling_id": "",
   "cause": ""
  },
  {
   "check": "C.referee_surge",
   "status": "PASS",
   "subject": "socialists",
   "evidence": "surge-agreement ok (referee ratio 0.9x, Detection 83.8)",
   "gap": "",
   "solution": "",
   "severity": "low",
   "task_class": "OPERATIONAL",
   "held_out_derived": true,
   "shadow": true,
   "ruling_id": "",
   "cause": ""
  },
  {
   "check": "C.referee_surge",
   "status": "PASS",
   "subject": "Andy Burnham",
   "evidence": "surge-agreement ok (referee ratio 3.1x, Detection 63.6)",
   "gap": "",
   "solution": "",
   "severity": "low",
   "task_class": "OPERATIONAL",
   "held_out_derived": true,
   "shadow": true,
   "ruling_id": "",
   "cause": ""
  },
  {
   "check": "C.referee_surge",
   "status": "PASS",
   "subject": "us and iran",
   "evidence": "surge-agreement ok (referee ratio 0.0x, Detection 37.4)",
   "gap": "",
   "solution": "",
   "severity": "low",
   "task_class": "OPERATIONAL",
   "held_out_derived": true,
   "shadow": true,
   "ruling_id": "",
   "cause": ""
  },
  {
   "check": "C.referee_surge",
   "status": "PASS",
   "subject": "hormuz",
   "evidence": "surge-agreement ok (referee ratio 1.1x, Detection 36.8)",
   "gap": "",
   "solution": "",
   "severity": "low",
   "task_class": "OPERATIONAL",
   "held_out_derived": true,
   "shadow": true,
   "ruling_id": "",
   "cause": ""
  },
  {
   "check": "C.referee_surge",
   "status": "PASS",
   "subject": "ai agents",
   "evidence": "surge-agreement ok (referee ratio 1.0x, Detection 50.9)",
   "gap": "",
   "solution": "",
   "severity": "low",
   "task_class": "OPERATIONAL",
   "held_out_derived": true,
   "shadow": true,
   "ruling_id": "",
   "cause": ""
  },
  {
   "check": "C.referee_surge",
   "status": "PASS",
   "subject": "fifa",
   "evidence": "surge-agreement ok (referee ratio 0.9x, Detection 26.0)",
   "gap": "",
   "solution": "",
   "severity": "low",
   "task_class": "OPERATIONAL",
   "held_out_derived": true,
   "shadow": true,
   "ruling_id": "",
   "cause": ""
  },
  {
   "check": "C.referee_surge",
   "status": "PASS",
   "subject": "rikers",
   "evidence": "surge-agreement ok (referee ratio 1.7x, Detection 94.2)",
   "gap": "",
   "solution": "",
   "severity": "low",
   "task_class": "OPERATIONAL",
   "held_out_derived": true,
   "shadow": true,
   "ruling_id": "",
   "cause": ""
  },
  {
   "check": "C.referee_surge",
   "status": "PASS",
   "subject": "agi",
   "evidence": "surge-agreement ok (referee ratio 0.8x, Detection 92.3)",
   "gap": "",
   "solution": "",
   "severity": "low",
   "task_class": "OPERATIONAL",
   "held_out_derived": true,
   "shadow": true,
   "ruling_id": "",
   "cause": ""
  },
  {
   "check": "C.referee_surge",
   "status": "PASS",
   "subject": "cyclospora",
   "evidence": "surge-agreement ok (referee ratio 18.9x, Detection 90.7)",
   "gap": "",
   "solution": "",
   "severity": "low",
   "task_class": "OPERATIONAL",
   "held_out_derived": true,
   "shadow": true,
   "ruling_id": "",
   "cause": ""
  },
  {
   "check": "C.referee_surge",
   "status": "PASS",
   "subject": "rag",
   "evidence": "surge-agreement ok (referee ratio 0.9x, Detection 65.0)",
   "gap": "",
   "solution": "",
   "severity": "low",
   "task_class": "OPERATIONAL",
   "held_out_derived": true,
   "shadow": true,
   "ruling_id": "",
   "cause": ""
  },
  {
   "check": "C.referee_surge",
   "status": "PASS",
   "subject": "taco bell",
   "evidence": "surge-agreement ok (referee ratio 2.1x, Detection 92.2)",
   "gap": "",
   "solution": "",
   "severity": "low",
   "task_class": "OPERATIONAL",
   "held_out_derived": true,
   "shadow": true,
   "ruling_id": "",
   "cause": ""
  },
  {
   "check": "C.referee_surge",
   "status": "PASS",
   "subject": "canada",
   "evidence": "surge-agreement ok (referee ratio 1.0x, Detection 88.4)",
   "gap": "",
   "solution": "",
   "severity": "low",
   "task_class": "OPERATIONAL",
   "held_out_derived": true,
   "shadow": true,
   "ruling_id": "",
   "cause": ""
  },
  {
   "check": "C.referee_surge",
   "status": "PASS",
   "subject": "wildfires",
   "evidence": "surge-agreement ok (referee ratio 3.6x, Detection 87.7)",
   "gap": "",
   "solution": "",
   "severity": "low",
   "task_class": "OPERATIONAL",
   "held_out_derived": true,
   "shadow": true,
   "ruling_id": "",
   "cause": ""
  },
  {
   "check": "C.referee_surge",
   "status": "INSUFFICIENT",
   "subject": "smoke from canada",
   "evidence": "referee unavailable (resolution_failed) \u2014 fail-open, and the cause is recorded truthfully (board N1)",
   "gap": "",
   "solution": "",
   "severity": "low",
   "task_class": "OPERATIONAL",
   "held_out_derived": false,
   "shadow": true,
   "ruling_id": "",
   "cause": "resolution_failed"
  },
  {
   "check": "C.referee_surge",
   "status": "PASS",
   "subject": "FIFA World Cup",
   "evidence": "surge-agreement ok (referee ratio 1.0x, Detection 82.1)",
   "gap": "",
   "solution": "",
   "severity": "low",
   "task_class": "OPERATIONAL",
   "held_out_derived": true,
   "shadow": true,
   "ruling_id": "",
   "cause": ""
  },
  {
   "check": "C.referee_surge",
   "status": "PASS",
   "subject": "russia",
   "evidence": "surge-agreement ok (referee ratio 0.0x, Detection 83.8)",
   "gap": "",
   "solution": "",
   "severity": "low",
   "task_class": "OPERATIONAL",
   "held_out_derived": true,
   "shadow": true,
   "ruling_id": "",
   "cause": ""
  },
  {
   "check": "C.referee_surge",
   "status": "PASS",
   "subject": "new mexico",
   "evidence": "surge-agreement ok (referee ratio 1.0x, Detection 80.8)",
   "gap": "",
   "solution": "",
   "severity": "low",
   "task_class": "OPERATIONAL",
   "held_out_derived": true,
   "shadow": true,
   "ruling_id": "",
   "cause": ""
  },
  {
   "check": "C.referee_surge",
   "status": "PASS",
   "subject": "drift-alarm datapoint",
   "evidence": "engine-referee rank correlation rho=0.14 on n=19 (series length 2; persisted to REFEREE_CORR_SERIES.json; a RISING trend = converging on a lagging fame index \u2014 alarm)",
   "gap": "",
   "solution": "",
   "severity": "low",
   "task_class": "OPERATIONAL",
   "held_out_derived": true,
   "shadow": true,
   "ruling_id": "",
   "cause": ""
  },
  {
   "check": "D.lifecycle",
   "status": "PASS",
   "subject": "mamdani",
   "evidence": "PEAKING \u2014 stage BREAKOUT consistent",
   "gap": "",
   "solution": "",
   "severity": "low",
   "task_class": "OPERATIONAL",
   "held_out_derived": false,
   "shadow": true,
   "ruling_id": "",
   "cause": ""
  },
  {
   "check": "D.lifecycle",
   "status": "PASS",
   "subject": "trump",
   "evidence": "PEAKING \u2014 stage BREAKOUT consistent",
   "gap": "",
   "solution": "",
   "severity": "low",
   "task_class": "OPERATIONAL",
   "held_out_derived": false,
   "shadow": true,
   "ruling_id": "",
   "cause": ""
  },
  {
   "check": "D.lifecycle",
   "status": "PASS",
   "subject": "mexico",
   "evidence": "PEAKING \u2014 stage STRONG consistent",
   "gap": "",
   "solution": "",
   "severity": "low",
   "task_class": "OPERATIONAL",
   "held_out_derived": false,
   "shadow": true,
   "ruling_id": "",
   "cause": ""
  },
  {
   "check": "D.lifecycle",
   "status": "PASS",
   "subject": "socialists",
   "evidence": "PEAKING \u2014 stage STRONG consistent",
   "gap": "",
   "solution": "",
   "severity": "low",
   "task_class": "OPERATIONAL",
   "held_out_derived": false,
   "shadow": true,
   "ruling_id": "",
   "cause": ""
  },
  {
   "check": "D.lifecycle",
   "status": "PASS",
   "subject": "andy_burnham",
   "evidence": "PEAKING \u2014 stage EMERGING consistent",
   "gap": "",
   "solution": "",
   "severity": "low",
   "task_class": "OPERATIONAL",
   "held_out_derived": false,
   "shadow": true,
   "ruling_id": "",
   "cause": ""
  },
  {
   "check": "D.lifecycle",
   "status": "PASS",
   "subject": "us_and_iran",
   "evidence": "PEAKING \u2014 stage WATCHING consistent",
   "gap": "",
   "solution": "",
   "severity": "low",
   "task_class": "OPERATIONAL",
   "held_out_derived": false,
   "shadow": true,
   "ruling_id": "",
   "cause": ""
  },
  {
   "check": "D.lifecycle",
   "status": "PASS",
   "subject": "strait_of_hormuz",
   "evidence": "STEADY \u2014 stage WATCHING consistent",
   "gap": "",
   "solution": "",
   "severity": "low",
   "task_class": "OPERATIONAL",
   "held_out_derived": false,
   "shadow": true,
   "ruling_id": "",
   "cause": ""
  },
  {
   "check": "D.lifecycle",
   "status": "PASS",
   "subject": "ai_agents",
   "evidence": "PEAKING \u2014 stage WATCHING consistent",
   "gap": "",
   "solution": "",
   "severity": "low",
   "task_class": "OPERATIONAL",
   "held_out_derived": false,
   "shadow": true,
   "ruling_id": "",
   "cause": ""
  },
  {
   "check": "D.lifecycle",
   "status": "PASS",
   "subject": "fifa",
   "evidence": "FADING \u2014 stage MONITORING consistent",
   "gap": "",
   "solution": "",
   "severity": "low",
   "task_class": "OPERATIONAL",
   "held_out_derived": false,
   "shadow": true,
   "ruling_id": "",
   "cause": ""
  },
  {
   "check": "D.lifecycle",
   "status": "PASS",
   "subject": "rikers",
   "evidence": "STEADY \u2014 stage BREAKOUT consistent",
   "gap": "",
   "solution": "",
   "severity": "low",
   "task_class": "OPERATIONAL",
   "held_out_derived": false,
   "shadow": true,
   "ruling_id": "",
   "cause": ""
  },
  {
   "check": "D.lifecycle",
   "status": "PASS",
   "subject": "agi",
   "evidence": "PEAKING \u2014 stage BREAKOUT consistent",
   "gap": "",
   "solution": "",
   "severity": "low",
   "task_class": "OPERATIONAL",
   "held_out_derived": false,
   "shadow": true,
   "ruling_id": "",
   "cause": ""
  },
  {
   "check": "D.lifecycle",
   "status": "PASS",
   "subject": "cyclospora",
   "evidence": "PEAKING \u2014 stage BREAKOUT consistent",
   "gap": "",
   "solution": "",
   "severity": "low",
   "task_class": "OPERATIONAL",
   "held_out_derived": false,
   "shadow": true,
   "ruling_id": "",
   "cause": ""
  },
  {
   "check": "D.lifecycle",
   "status": "PASS",
   "subject": "rag",
   "evidence": "STEADY \u2014 stage BREAKOUT consistent",
   "gap": "",
   "solution": "",
   "severity": "low",
   "task_class": "OPERATIONAL",
   "held_out_derived": false,
   "shadow": true,
   "ruling_id": "",
   "cause": ""
  },
  {
   "check": "D.lifecycle",
   "status": "PASS",
   "subject": "taco_bell",
   "evidence": "PEAKING \u2014 stage BREAKOUT consistent",
   "gap": "",
   "solution": "",
   "severity": "low",
   "task_class": "OPERATIONAL",
   "held_out_derived": false,
   "shadow": true,
   "ruling_id": "",
   "cause": ""
  },
  {
   "check": "D.lifecycle",
   "status": "PASS",
   "subject": "canada",
   "evidence": "STEADY \u2014 stage BREAKOUT consistent",
   "gap": "",
   "solution": "",
   "severity": "low",
   "task_class": "OPERATIONAL",
   "held_out_derived": false,
   "shadow": true,
   "ruling_id": "",
   "cause": ""
  },
  {
   "check": "E.trending_recall",
   "status": "INSUFFICIENT",
   "subject": "google daily trending",
   "evidence": "no external items qualified today (scanned 2000/3353 served topics; 0 matchup-class excluded; 10 below the 10,000 traffic floor) \u2014 an honest no-grade day, like the crypto check's 'no 20% movers'",
   "gap": "",
   "solution": "",
   "severity": "low",
   "task_class": "OPERATIONAL",
   "held_out_derived": false,
   "shadow": false,
   "ruling_id": "",
   "cause": "no_qualifying_items"
  },
  {
   "check": "E.crypto_agreement",
   "status": "INSUFFICIENT",
   "subject": "crypto movers",
   "evidence": "no 20% movers this week (nothing to grade)",
   "gap": "",
   "solution": "",
   "severity": "low",
   "task_class": "OPERATIONAL",
   "held_out_derived": false,
   "shadow": true,
   "ruling_id": "",
   "cause": ""
  }
 ],
 "work_queue": [
  {
   "check": "B.freeze",
   "status": "FAIL",
   "subject": "final_del_mundial",
   "evidence": "Detection identical at 62.59 for 6 cycles while mentions varied 10\u201316",
   "gap": "score not responding to changing inputs (possible cached serve or saturated components)",
   "solution": "check INV-1 serve-stored rules + serve_payload freshness for this row; inspect component values in the detail; report findings to the founder before any scoring change",
   "severity": "high",
   "task_class": "SCORE_AFFECTING",
   "held_out_derived": false,
   "shadow": false,
   "ruling_id": "",
   "cause": ""
  },
  {
   "check": "B.asymmetry",
   "status": "WARN",
   "subject": "britain",
   "evidence": "instant transitions BOTH ways in one window (max up 51.6, max down -51.5 in single cycles) \u2014 artifact signature, not attention dynamics",
   "gap": "quantized bistability: the estimator, not the phenomenon, is moving",
   "solution": "hold for the cohort replay verification (board Q1/Q2 item 3); no estimator change without founder + backtest (item 6 HELD)",
   "severity": "low",
   "task_class": "OPERATIONAL",
   "held_out_derived": false,
   "shadow": true,
   "ruling_id": "",
   "cause": ""
  }
 ]
}